odoo/addons/l10n_br_resource/README.rst
odoo/addons/l10n_br_resource/__init__.py
odoo/addons/l10n_br_resource/__manifest__.py
odoo/addons/l10n_br_resource/i18n/l10n_br_resource.pot
odoo/addons/l10n_br_resource/i18n/pt_BR.po
odoo/addons/l10n_br_resource/models/__init__.py
odoo/addons/l10n_br_resource/models/resource_calendar.py
odoo/addons/l10n_br_resource/models/resource_calendar_leaves.py
odoo/addons/l10n_br_resource/readme/CONFIGURE.rst
odoo/addons/l10n_br_resource/readme/CONTRIBUTORS.rst
odoo/addons/l10n_br_resource/readme/CREDITS.rst
odoo/addons/l10n_br_resource/readme/DESCRIPTION.rst
odoo/addons/l10n_br_resource/readme/HISTORY.rst
odoo/addons/l10n_br_resource/readme/INSTALL.rst
odoo/addons/l10n_br_resource/readme/ROADMAP.rst
odoo/addons/l10n_br_resource/readme/USAGE.rst
odoo/addons/l10n_br_resource/static/description/icon.png
odoo/addons/l10n_br_resource/static/description/icon.svg.oca
odoo/addons/l10n_br_resource/static/description/index.html
odoo/addons/l10n_br_resource/tests/__init__.py
odoo/addons/l10n_br_resource/tests/test_resource_calendar.py
odoo/addons/l10n_br_resource/tools/__init__.py
odoo/addons/l10n_br_resource/tools/brazil_all_holidays_set.py
odoo/addons/l10n_br_resource/views/resource_calendar_leaves_view.xml
odoo/addons/l10n_br_resource/views/resource_calendar_menu.xml
odoo/addons/l10n_br_resource/views/resource_calendar_view.xml
odoo/addons/l10n_br_resource/wizards/__init__.py
odoo/addons/l10n_br_resource/wizards/workalendar_holiday_import_views.xml
odoo/addons/l10n_br_resource/wizards/workalendar_holiday_import_wizard.py
odoo12_addon_l10n_br_resource-12.0.1.1.0.dist-info/METADATA
odoo12_addon_l10n_br_resource-12.0.1.1.0.dist-info/WHEEL
odoo12_addon_l10n_br_resource-12.0.1.1.0.dist-info/top_level.txt
odoo12_addon_l10n_br_resource-12.0.1.1.0.dist-info/RECORD
