Metadata-Version: 2.1
Name: odoo12-addon-l10n-br-resource
Version: 12.0.1.1.0
Summary: This module extend core resource to create important brazilian informations. Define a Brazilian calendar and some tools to compute dates used in financial and payroll modules
Home-page: https://github.com/OCA/l10n-brazil
Author: KMEE,Odoo Community Association (OCA)
Author-email: support@odoo-community.org
License: AGPL-3
Platform: UNKNOWN
Classifier: Programming Language :: Python
Classifier: Framework :: Odoo
Classifier: License :: OSI Approved :: GNU Affero General Public License v3
Requires-Python: >=3.5
Requires-Dist: odoo12-addon-l10n-br-base
Requires-Dist: odoo (<12.1dev,>=12.0a)
Requires-Dist: workalendar
